101703375_p2-0.1.0.data/scripts/outcli
outlib/__init__.py
outlib/p2.py
101703375_p2-0.1.0.dist-info/METADATA
101703375_p2-0.1.0.dist-info/WHEEL
101703375_p2-0.1.0.dist-info/top_level.txt
101703375_p2-0.1.0.dist-info/RECORD
